stormreply/cdk_openapi/__init__.py
stormreply/cdk_openapi/py.typed
stormreply/cdk_openapi/_jsii/__init__.py
stormreply/cdk_openapi/_jsii/cdk-openapi@0.0.6.jsii.tgz
stormreply.cdk_openapi-0.0.6.dist-info/METADATA
stormreply.cdk_openapi-0.0.6.dist-info/WHEEL
stormreply.cdk_openapi-0.0.6.dist-info/top_level.txt
stormreply.cdk_openapi-0.0.6.dist-info/RECORD
